pyconn_monitor/__init__.py
pyconn_monitor/cli.py
pyconn_monitor/connection_monitor.py
pyconn_monitor-0.1.6.dist-info/LICENSE
pyconn_monitor-0.1.6.dist-info/METADATA
pyconn_monitor-0.1.6.dist-info/WHEEL
pyconn_monitor-0.1.6.dist-info/entry_points.txt
pyconn_monitor-0.1.6.dist-info/top_level.txt
pyconn_monitor-0.1.6.dist-info/RECORD
