Metadata-Version: 2.1
Name: pyconn-monitor
Version: 0.1.6
Summary: A Python library to monitor and log network connections of untrusted programs
Home-page: https://github.com/ParisNeo/pyconn-monitor
Author: ParisNeo
Author-email: parisneoai@gmail.com
Classifier: Development Status :: 3 - Alpha
Classifier: Intended Audience :: Developers
Classifier: License :: OSI Approved :: Apache Software License
Classifier: Programming Language :: Python :: 3
Classifier: Programming Language :: Python :: 3.6
Classifier: Programming Language :: Python :: 3.7
Classifier: Programming Language :: Python :: 3.8
Classifier: Programming Language :: Python :: 3.9
Classifier: Programming Language :: Python :: 3.10
Classifier: Programming Language :: Python :: 3.11
Classifier: Programming Language :: Python :: 3.12
License-File: LICENSE
Requires-Dist: psutil
Requires-Dist: ascii-colors
